tests.py
vuid-0.1.0.dist-info/METADATA
vuid-0.1.0.dist-info/WHEEL
vuid-0.1.0.dist-info/entry_points.txt
vuid-0.1.0.dist-info/licenses/LICENSE
vuid.py
vuid-0.1.0.dist-info/RECORD
