Metadata-Version: 2.1
Name: vuid
Version: 0.1.0
Summary: Vahid Unique ID Generator
Classifier: License :: OSI Approved :: Apache Software License
Classifier: Programming Language :: Python
Classifier: Programming Language :: Python :: 3
Requires-Python: >=3.8
